pji/__init__.py
pji/config/__init__.py
pji/config/meta.py
pji/control/__init__.py
pji/control/model/__init__.py
pji/control/model/identification.py
pji/control/model/process.py
pji/control/model/resource.py
pji/control/model/run.py
pji/control/model/timing.py
pji/control/process/__init__.py
pji/control/process/base.py
pji/control/process/common.py
pji/control/process/decorator.py
pji/control/process/executor.py
pji/control/process/interactive.py
pji/control/run/__init__.py
pji/control/run/common.py
pji/control/run/encoding.py
pji/control/run/mutual.py
pji/control/run/timing.py
pji/entry/__init__.py
pji/entry/event.py
pji/entry/runner.py
pji/entry/cli/__init__.py
pji/entry/cli/cli.py
pji/entry/cli/environ.py
pji/entry/cli/event.py
pji/entry/cli/exception.py
pji/entry/script/__init__.py
pji/entry/script/event.py
pji/entry/script/execute.py
pji/entry/script/result.py
pji/service/__init__.py
pji/service/base.py
pji/service/command/__init__.py
pji/service/command/base.py
pji/service/command/collection.py
pji/service/command/command.py
pji/service/command/template.py
pji/service/dispatch/__init__.py
pji/service/dispatch/dispatch.py
pji/service/dispatch/global_.py
pji/service/section/__init__.py
pji/service/section/info/__init__.py
pji/service/section/info/base.py
pji/service/section/info/general.py
pji/service/section/info/local.py
pji/service/section/info/mapping.py
pji/service/section/info/static.py
pji/service/section/info/tag.py
pji/service/section/input/__init__.py
pji/service/section/input/base.py
pji/service/section/input/collection.py
pji/service/section/input/copy.py
pji/service/section/input/general.py
pji/service/section/input/link.py
pji/service/section/input/tag.py
pji/service/section/output/__init__.py
pji/service/section/output/base.py
pji/service/section/output/collection.py
pji/service/section/output/copy.py
pji/service/section/output/general.py
pji/service/section/output/tag.py
pji/service/section/section/__init__.py
pji/service/section/section/base.py
pji-0.2.2.dist-info/LICENSE
pji-0.2.2.dist-info/METADATA
pji-0.2.2.dist-info/WHEEL
pji-0.2.2.dist-info/entry_points.txt
pji-0.2.2.dist-info/top_level.txt
pji-0.2.2.dist-info/RECORD
